llamaverify/__init__.py
llamaverify/client.py
llamaverify-0.1.6.dist-info/METADATA
llamaverify-0.1.6.dist-info/WHEEL
llamaverify-0.1.6.dist-info/top_level.txt
llamaverify-0.1.6.dist-info/RECORD
