Metadata-Version: 2.1
Name: llamaverify
Version: 0.1.6
Summary: A package for dehallucinating LLM outputs.
Author: Your Name
Author-email: your.email@example.com
Classifier: Programming Language :: Python :: 3
Classifier: License :: OSI Approved :: MIT License
Classifier: Operating System :: OS Independent
Requires-Dist: huggingface-hub
Requires-Dist: requests
